data49/__init__.py
data49/_hypercache.py
data49/internal.py
data49/py.typed
data49/web.py
data49-0.4.4.dist-info/WHEEL
data49-0.4.4.dist-info/METADATA
data49-0.4.4.dist-info/RECORD
