Metadata-Version: 2.1
Name: data49
Version: 0.4.4
Summary: A gold rush-themed data mining library
Author: Bryan Hu
Author-email: bryan.hu.2020@gmail.com
Requires-Python: >=3.7,<4.0
Classifier: Programming Language :: Python :: 3
Classifier: Programming Language :: Python :: 3.10
Classifier: Programming Language :: Python :: 3.7
Classifier: Programming Language :: Python :: 3.8
Classifier: Programming Language :: Python :: 3.9
Requires-Dist: beautifulsoup4 (>=4.10.0,<5.0.0)
Requires-Dist: requests (>=2.27.1,<3.0.0)
Requires-Dist: selenium (>=4.3.0,<5.0.0)
Requires-Dist: thefuzz[speedup] (>=0.19.0,<0.20.0)
